main.py
numpy/__init__.py
numpy/cli.py
numpy/continuous_opt_ga.py
numpy/eight_queens_ga.py
numpy/graph_coloring_ga.py
numpy/knapsack_ga.py
numpy/linear_equation_ga.py
numpy/runner.py
numpy/symbolic_gp.py
numpy/tsp_ga.py
npygenx-0.4.0.dist-info/METADATA
npygenx-0.4.0.dist-info/WHEEL
npygenx-0.4.0.dist-info/entry_points.txt
npygenx-0.4.0.dist-info/top_level.txt
npygenx-0.4.0.dist-info/RECORD
